awsslack/__init__.py
awsslack/__main__.py
awsslack/commands/__init__.py
awsslack/commands/codebuild.py
awsslack/commands/codedeploy.py
awsslack/commands/config.py
awsslack/main.py
awsslack/utils/__init__.py
awsslack/utils/code_build.py
awsslack/utils/code_deploy.py
awsslack/utils/yaml.py
awsslack-0.1.4.dist-info/METADATA
awsslack-0.1.4.dist-info/WHEEL
awsslack-0.1.4.dist-info/entry_points.txt
awsslack-0.1.4.dist-info/RECORD
