Metadata-Version: 2.1
Name: awsslack
Version: 0.1.4
Summary: AWS CodeBuild/CodeDeploy triggers & updates to Slack with a cool Progress Bar!
License: MIT
Author: Saurabh Chopra
Author-email: Saurabh.Chopra.2021@live.rhul.ac.uk
Requires-Python: >=3.8,<4.0
Classifier: License :: OSI Approved :: MIT License
Classifier: Programming Language :: Python :: 3
Classifier: Programming Language :: Python :: 3.8
Classifier: Programming Language :: Python :: 3.9
Classifier: Programming Language :: Python :: 3.10
Classifier: Programming Language :: Python :: 3.11
Requires-Dist: boto3 (>=1.26.91,<2.0.0)
Requires-Dist: pyyaml (>=6.0,<7.0)
Requires-Dist: slack-sdk (>=3.20.2,<4.0.0)
